complaince/complaince.py
complaince/__init__.py
complaince-1.0.2.0b0.dev2.dist-info/pbr.json
complaince-1.0.2.0b0.dev2.dist-info/WHEEL
complaince-1.0.2.0b0.dev2.dist-info/top_level.txt
complaince-1.0.2.0b0.dev2.dist-info/metadata.json
complaince-1.0.2.0b0.dev2.dist-info/DESCRIPTION.rst
complaince-1.0.2.0b0.dev2.dist-info/METADATA
complaince-1.0.2.0b0.dev2.dist-info/RECORD
