Metadata-Version: 2.0
Name: complaince
Version: 1.0.2.0b0.dev2
Summary: A python function parameter and return type-checking decorator
Home-page: https://github.com/vrakesh/Complaince
Author: Rakesh Vasudevan
Author-email: UNKNOWN
License: 'Apache'
Platform: UNKNOWN
Classifier: Development Status :: 4 - Beta
Classifier: Intended Audience :: Developers
Classifier: Operating System :: POSIX :: Linux
Classifier: Programming Language :: Python
Classifier: Programming Language :: Python :: 2.6
Classifier: Programming Language :: Python :: 2.7
Classifier: Programming Language :: Python :: 3.3
Classifier: Programming Language :: Python :: 3.4
